{
  "task_id": "aime2025_i_06",
  "user_prompt": "An isosceles trapezoid has an inscribed circle tangent to each of its four sides. The radius of the circle is 3, and the area of the trapezoid is 72. Let the parallel sides of the trapezoid have lengths $r$ and $s$, with $r \\neq s$. Find $r^{2}+s^{2}$.",
  "expected_regex": "(?m)^\\s*504\\s*$",
  "stop_reason": "eos",
  "new_tokens": 4112,
  "checkpoint_meta": {
    "first_think_budget_tokens": 5000,
    "first_think_budget_triggered": false,
    "first_think_budget_forced_close_applied": false,
    "first_think_budget_forced_close_text": null,
    "prefix_tokens_before_plain_continuation": 3152
  },
  "metrics": {
    "think_balanced": true,
    "expected_hit_raw": false,
    "expected_hit": false
  }
}